j2s3/__init__.py
j2s3/file_service.py
j2s3/iam_policy.py
j2s3/main.py
j2s3/maven_service.py
j2s3/pom.py
j2s3/settings.py
j2s3/xml_service.py
j2s3-1.0.2.dist-info/METADATA
j2s3-1.0.2.dist-info/RECORD
j2s3-1.0.2.dist-info/WHEEL
j2s3-1.0.2.dist-info/top_level.txt
