Metadata-Version: 2.1
Name: j2s3
Version: 1.0.2
Summary: A lib for publishing Java maven projects to an S3 maven repository
Home-page: https://github.com/jackmahoney/j2s3
Author: jackmahoney
Author-email: jackmahoney212@gmail.com
License: Apache 2.0
Platform: UNKNOWN
Requires-Dist: pytest (==3.8.0)
Requires-Dist: lxml (==4.2.4)
